versioneye_slack
